{
  "$schema": "../node_modules/json-server/schema.json",
  "settings": [
    {
      "key": "core-qlik-application-id",
      "value": "C:\\Users\\Monday\\Documents\\Qlik\\Sense\\Apps\\app1.qvf",
      "id": "khPID62EKUo"
    }
  ],
  "dashboards": [
    {
      "id": "4d8b396d-f1df-4f77-b970-7f5120f5f383",
      "name": "Dashboard 1"
    },
    {
      "id": "762f0e87-6f4d-4f1b-8e86-1578264953f8",
      "name": "Dashboard 2"
    }
  ],
  "widgets": [
    {
      "id": "0fd0a8c1-b797-46d9-bbd1-4a08f6e6fce1",
      "name": "Revenue Overview",
      "qlikApplicationId": "2c188ab2-2eb8-4a55-bf9f-cad0d65b0fc3",
      "objectId": "7d2b2e66-12f7-484f-b3a0-5f0c1267cd3f",
      "type": "barchart"
    },
    {
      "name": "Normal Table",
      "qlikApplicationId": "ac706353-d1ae-415d-a8e2-1daa163e8d84",
      "objectId": "6b056ca8-0979-4b1e-983c-8d5542673197",
      "type": "table",
      "id": "M1x5952EDHY"
    }
  ],
  "dashboardWidgets": [
    {
      "id": "71088f87-0d00-4d15-94ca-f1308fd39263",
      "dashboardId": "4d8b396d-f1df-4f77-b970-7f5120f5f383",
      "widgetId": "0fd0a8c1-b797-46d9-bbd1-4a08f6e6fce1"
    },
    {
      "dashboardId": "4d8b396d-f1df-4f77-b970-7f5120f5f383",
      "widgetId": "M1x5952EDHY",
      "id": "8Aq5mrA7ZD8"
    }
  ],
  "filters": [
    {
      "dashboardId": "4d8b396d-f1df-4f77-b970-7f5120f5f383",
      "widgetId": null,
      "type": "hierarchy",
      "filterHierarchyId": "805f31cc-1cdf-4ff1-91d3-8444ddf1045d",
      "fieldName": null,
      "id": "tFHeqNcKn1c",
      "defaultValuesJson": "",
      "allowedValuesJson": "{\"version\": 2,\"fields\": {\"Segment\": {\"fieldLabel\": \"segs\", \"options\": [\"C1\", \"C2\"], \"automaticVisibility\": false},\"Product Group\": {\"fieldLabel\": \"\", \"options\": [], \"automaticVisibility\": true}}}"
    },
    {
      "dashboardId": "4d8b396d-f1df-4f77-b970-7f5120f5f383",
      "widgetId": "0fd0a8c1-b797-46d9-bbd1-4a08f6e6fce1",
      "type": "field",
      "filterHierarchyId": "",
      "fieldName": "Segment",
      "id": "GAC6m9VFJmk"
    },
    {
      "dashboardId": "4d8b396d-f1df-4f77-b970-7f5120f5f383",
      "widgetId": "0fd0a8c1-b797-46d9-bbd1-4a08f6e6fce1",
      "type": "hierarchy",
      "filterHierarchyId": "805f31cc-1cdf-4ff1-91d3-8444ddf1045d",
      "fieldName": null,
      "id": "pAbo1nCyeqA"
    },
    {
      "dashboardId": "4d8b396d-f1df-4f77-b970-7f5120f5f383",
      "widgetId": "M1x5952EDHY",
      "type": "hierarchy",
      "filterHierarchyId": "805f31cc-1cdf-4ff1-91d3-8444ddf1045d",
      "fieldName": null,
      "id": "-epXvndFMkA"
    },
    {
      "dashboardId": "4d8b396d-f1df-4f77-b970-7f5120f5f383",
      "widgetId": "M1x5952EDHY",
      "type": "field",
      "filterHierarchyId": "",
      "fieldName": "Segment",
      "id": "FgkjZR2352I"
    }
  ],
  "hierarchies": [
    {
      "id": "805f31cc-1cdf-4ff1-91d3-8444ddf1045d",
      "name": "Product",
      "fields": [
        {
          "id": "b0044c08-1b08-46a8-bf9c-60450991c965",
          "fieldName": "Segment"
        },
        {
          "id": "f1664483-ea8c-472f-a48a-8450fca899f7",
          "fieldName": "Product Group"
        },
        {
          "id": "5f3d25d9-3591-43b4-bc93-b83450fc7bf4",
          "fieldName": "Product Sub Group"
        },
        {
          "id": "1c534827-f402-42a4-8284-0080e203f37c",
          "fieldName": "Product"
        }
      ]
    }
  ],
  "qlikApplications": [
    {
      "id": "2c188ab2-2eb8-4a55-bf9f-cad0d65b0fc3",
      "name": "app1",
      "appId": "C:\\Users\\Monday\\Documents\\Qlik\\Sense\\Apps\\app1.qvf"
    },
    {
      "id": "ac706353-d1ae-415d-a8e2-1daa163e8d84",
      "name": "app2",
      "appId": "C:\\Users\\Monday\\Documents\\Qlik\\Sense\\Apps\\app2.qvf"
    }
  ]
}